{"paths":{"0":["com-btn-switch-click",0],"1":["error",0],"2":["flow",0],"3":["gainkey",0],"4":["pick",0],"5":["pick2",0],"6":["put",0],"7":["put2",0],"8":["success",0],"9":["swap",0],"10":["unlock",0]},"types":["cc.AudioClip"],"uuids":["c67rDcQiNEoZCuvh4NPfAC","eeTuBYvu9PBbQARBCEBdiR","47ySKeRl1LN6UPZj4DhVKz","95A31dWL9JkoxIuvr47x47","57iAcw5p9KhatOhXG63tAR","70wtyvL5FDtIvpN6fbV4n0","f3+Irc/NZNQ7AqFcQIdfFi","7dK9MmgmdIALfkDJ2YiGeI","f1Siyi5d1EC4HDEGOmBWCG","a5N3x8n1ZG6Y61fMkdE3Zh","ab0Qyy2MdHC7ki9q/eN6B8"],"scenes":{},"redirect":[],"deps":[],"packs":{},"name":"sfx","importBase":"import","nativeBase":"native","debug":false,"isZip":false,"encrypted":false,"versions":{"import":[2,"96425",4,"302eb",5,"51ab1",7,"999e7",3,"3797e",9,"0e888",10,"512e2",0,"5be8b",1,"6d4f9",8,"13182",6,"2765b"],"native":[2,"2e134",4,"abdd6",5,"b480e",7,"ce4ee",3,"247fb",9,"9921f",10,"a6ed9",0,"f6e42",1,"f7a09",8,"c5c4e",6,"fb054"]}}